[{"id":1,"image":"https://storage.googleapis.com/images_station/CT.png","link":"https://www.facebook.com/CrazyTown.Agency/","location":"Baghdad","published_at":"2021-04-14T17:10:00.420Z","created_at":"2021-04-14T17:02:46.473Z","updated_at":"2021-04-14T17:15:04.012Z"},{"id":2,"image":"https://storage.googleapis.com/images_station/05176330-7107-11ea-8d15-71dcf03762b5.png","link":"https://www.facebook.com/eyen.agency/","location":"Baghdad","published_at":"2021-04-14T17:10:02.373Z","created_at":"2021-04-14T17:03:07.545Z","updated_at":"2021-04-14T17:15:07.241Z"},{"id":3,"image":"https://storage.googleapis.com/images_station/shabab1-1.png","link":"https://www.facebook.com/Shabab.media.iq","location":"Baghdad","published_at":"2021-04-14T17:09:37.344Z","created_at":"2021-04-14T17:04:09.572Z","updated_at":"2021-04-14T17:15:10.042Z"},{"id":4,"image":"https://storage.googleapis.com/images_station/PB.png","link":"https://www.facebook.com/1233372160135334/posts/1246753525463864/?d=n&substory_index=0","location":"Baghdad","published_at":"2021-04-14T17:09:58.160Z","created_at":"2021-04-14T17:04:24.881Z","updated_at":"2021-04-14T17:15:13.591Z"},{"id":5,"image":"https://storage.googleapis.com/images_station/advenature.png","link":"https://www.facebook.com/AdvenatureIQ/","location":"Baghdad","published_at":"2021-04-14T17:09:53.481Z","created_at":"2021-04-14T17:04:39.911Z","updated_at":"2021-04-14T17:15:16.680Z"},{"id":6,"image":"https://storage.googleapis.com/images_station/space0002.png","link":"https://www.facebook.com/space.2.palce/","location":"Baghdad","published_at":"2021-04-14T17:09:34.633Z","created_at":"2021-04-14T17:05:11.063Z","updated_at":"2021-04-14T17:15:25.971Z"},{"id":7,"image":"https://storage.googleapis.com/images_station/chif.png","link":"https://www.facebook.com/chafyia/","location":"Baghdad","published_at":"2021-04-14T17:09:49.057Z","created_at":"2021-04-14T17:05:23.035Z","updated_at":"2021-04-14T17:15:23.100Z"},{"id":8,"image":"https://storage.googleapis.com/images_station/acad.png","link":"https://www.facebook.com/CADacademy.iq/","location":"Baghdad","published_at":"2021-04-14T17:09:55.706Z","created_at":"2021-04-14T17:05:43.594Z","updated_at":"2021-04-14T17:16:41.310Z"},{"id":9,"image":"https://i.ibb.co/g6gzFT3/Whats-App-Image-2019-09-02-at-5-33-10-PM.jpg","link":"https://wasil-iq.com/","location":"Baghdad","published_at":"2021-04-14T17:10:15.018Z","created_at":"2021-04-14T17:06:02.410Z","updated_at":"2021-04-14T17:14:58.525Z"},{"id":11,"image":"https://i.ibb.co/n3k67PW/119000458-661713837780463-7663832019910098832-o.jpg","link":"https://www.facebook.com/ariikaIraq","location":"Baghdad","published_at":"2021-04-14T17:10:13.137Z","created_at":"2021-04-14T17:06:53.125Z","updated_at":"2021-04-14T17:16:50.493Z"},{"id":12,"image":"https://i.ibb.co/KscdCBS/iot.png","link":"https://www.facebook.com/IoTLAB.info/","location":"Baghdad","published_at":"2021-04-14T17:10:26.890Z","created_at":"2021-04-14T17:07:15.151Z","updated_at":"2021-04-14T17:14:41.985Z"},{"id":13,"image":"https://i.ibb.co/wWwQhbQ/toastmasters.png","link":"https://www.facebook.com/BaghdadToastmasters","location":"Baghdad","published_at":"2021-04-14T17:10:04.707Z","created_at":"2021-04-14T17:07:29.704Z","updated_at":"2021-04-14T17:16:55.385Z"},{"id":14,"image":"https://i.ibb.co/ZHn9xRQ/miq.png","link":"https://www.facebook.com/WorldMeritIraq","location":"Baghdad","published_at":"2021-04-14T17:10:17.389Z","created_at":"2021-04-14T17:07:42.068Z","updated_at":"2021-04-14T17:14:51.686Z"},{"id":15,"image":"https://storage.googleapis.com/images_station/ashnona-(1).png","link":"https://www.facebook.com/Ashnuna1","location":"Baghdad","published_at":"2021-04-14T17:09:51.369Z","created_at":"2021-04-14T17:07:58.293Z","updated_at":"2021-04-14T17:17:00.508Z"},{"id":16,"image":"https://i.ibb.co/WKXHh31/Sumar-Legend1.png","link":"https://www.facebook.com/sumar.iraq","location":"Baghdad","published_at":"2021-04-14T17:10:19.374Z","created_at":"2021-04-14T17:08:17.459Z","updated_at":"2021-04-14T17:14:48.849Z"},{"id":17,"image":"https://i.ibb.co/MhyDgwL/144876730-5057531084319022-2379886864631321284-o-jpg.png","link":"https://www.facebook.com/razi.care/","location":"Baghdad","published_at":"2021-04-14T17:10:21.765Z","created_at":"2021-04-14T17:08:57.801Z","updated_at":"2021-04-14T17:14:45.526Z"},{"id":18,"image":"https://i.ibb.co/sPTVP22/Picture1.png","link":"https://www.facebook.com/MaslahTech-%D9%85%D8%B5%D9%84%D8%AD%D8%AA%D9%83-103907308322957","location":"Baghdad","published_at":"2021-04-14T17:10:10.668Z","created_at":"2021-04-14T17:09:11.026Z","updated_at":"2021-04-14T17:17:07.686Z"}]
